odoo8_addon_l10n_ch_bank-8.0.9.0.0.99.dev13-nspkg.pth
odoo_addons/l10n_ch_bank/README.rst
odoo_addons/l10n_ch_bank/__init__.py
odoo_addons/l10n_ch_bank/__openerp__.py
odoo_addons/l10n_ch_bank/bank.py
odoo_addons/l10n_ch_bank/bank.xml
odoo_addons/l10n_ch_bank/res_config.py
odoo_addons/l10n_ch_bank/res_config_view.xml
odoo_addons/l10n_ch_bank/i18n/ca.po
odoo_addons/l10n_ch_bank/i18n/de.po
odoo_addons/l10n_ch_bank/i18n/es.po
odoo_addons/l10n_ch_bank/i18n/fi.po
odoo_addons/l10n_ch_bank/i18n/fr.po
odoo_addons/l10n_ch_bank/i18n/hr.po
odoo_addons/l10n_ch_bank/i18n/it.po
odoo_addons/l10n_ch_bank/i18n/l10n_ch_bank.pot
odoo_addons/l10n_ch_bank/i18n/pt.po
odoo_addons/l10n_ch_bank/i18n/sl.po
odoo_addons/l10n_ch_bank/migrations/8.0.9.0.0/pre-migration.py
odoo_addons/l10n_ch_bank/static/description/icon.png
odoo8_addon_l10n_ch_bank-8.0.9.0.0.99.dev13.dist-info/METADATA
odoo8_addon_l10n_ch_bank-8.0.9.0.0.99.dev13.dist-info/WHEEL
odoo8_addon_l10n_ch_bank-8.0.9.0.0.99.dev13.dist-info/namespace_packages.txt
odoo8_addon_l10n_ch_bank-8.0.9.0.0.99.dev13.dist-info/top_level.txt
odoo8_addon_l10n_ch_bank-8.0.9.0.0.99.dev13.dist-info/RECORD
